<?xml version="1.0" encoding="UTF-8"?>
<checkstyle version="5.0">
    <file name="c:\dev\kicad-personal\common\gestfich.cpp">
        <error source="T008" severity="info" line="46" message="keyword &apos;if&apos; not followed by a single space" />
        <error source="T012" severity="info" line="46" message="negation operator used in its short form" />
        <error source="T008" severity="info" line="71" message="keyword &apos;if&apos; not followed by a single space" />
        <error source="T008" severity="info" line="104" message="keyword &apos;if&apos; not followed by a single space" />
        <error source="T008" severity="info" line="106" message="keyword &apos;if&apos; not followed by a single space" />
        <error source="T019" severity="info" line="107" message="full block {} expected in the control structure" />
        <error source="T019" severity="info" line="109" message="full block {} expected in the control structure" />
        <error source="L004" severity="info" line="115" message="line is longer than 100 characters" />
        <error source="T008" severity="info" line="133" message="keyword &apos;if&apos; not followed by a single space" />
        <error source="T019" severity="info" line="134" message="full block {} expected in the control structure" />
        <error source="T008" severity="info" line="136" message="keyword &apos;if&apos; not followed by a single space" />
        <error source="T012" severity="info" line="136" message="negation operator used in its short form" />
        <error source="T008" severity="info" line="155" message="keyword &apos;if&apos; not followed by a single space" />
        <error source="T019" severity="info" line="156" message="full block {} expected in the control structure" />
        <error source="T008" severity="info" line="160" message="keyword &apos;if&apos; not followed by a single space" />
        <error source="T008" severity="info" line="164" message="keyword &apos;if&apos; not followed by a single space" />
        <error source="T019" severity="info" line="165" message="full block {} expected in the control structure" />
        <error source="T011" severity="info" line="188" message="closing curly bracket not in the same line or column" />
        <error source="T008" severity="info" line="191" message="keyword &apos;for&apos; not followed by a single space" />
        <error source="T008" severity="info" line="200" message="keyword &apos;if&apos; not followed by a single space" />
        <error source="T019" severity="info" line="201" message="full block {} expected in the control structure" />
        <error source="T008" severity="info" line="213" message="keyword &apos;if&apos; not followed by a single space" />
        <error source="T008" severity="info" line="215" message="keyword &apos;if&apos; not followed by a single space" />
        <error source="T012" severity="info" line="215" message="negation operator used in its short form" />
        <error source="T019" severity="info" line="216" message="full block {} expected in the control structure" />
        <error source="T008" severity="info" line="225" message="keyword &apos;if&apos; not followed by a single space" />
        <error source="T012" severity="info" line="225" message="negation operator used in its short form" />
        <error source="T019" severity="info" line="226" message="full block {} expected in the control structure" />
        <error source="T008" severity="info" line="244" message="keyword &apos;if&apos; not followed by a single space" />
        <error source="T008" severity="info" line="256" message="keyword &apos;if&apos; not followed by a single space" />
        <error source="T008" severity="info" line="261" message="keyword &apos;if&apos; not followed by a single space" />
        <error source="T019" severity="info" line="262" message="full block {} expected in the control structure" />
        <error source="T008" severity="info" line="273" message="keyword &apos;if&apos; not followed by a single space" />
        <error source="T008" severity="info" line="277" message="keyword &apos;if&apos; not followed by a single space" />
        <error source="T008" severity="info" line="285" message="keyword &apos;if&apos; not followed by a single space" />
        <error source="T012" severity="info" line="285" message="negation operator used in its short form" />
        <error source="T011" severity="info" line="310" message="closing curly bracket not in the same line or column" />
        <error source="T008" severity="info" line="312" message="keyword &apos;for&apos; not followed by a single space" />
        <error source="T008" severity="info" line="316" message="keyword &apos;if&apos; not followed by a single space" />
        <error source="T008" severity="info" line="329" message="keyword &apos;if&apos; not followed by a single space" />
        <error source="T008" severity="info" line="333" message="keyword &apos;if&apos; not followed by a single space" />
        <error source="T019" severity="info" line="334" message="full block {} expected in the control structure" />
        <error source="T008" severity="info" line="355" message="keyword &apos;if&apos; not followed by a single space" />
        <error source="T012" severity="info" line="355" message="negation operator used in its short form" />
        <error source="T008" severity="info" line="361" message="keyword &apos;if&apos; not followed by a single space" />
        <error source="T019" severity="info" line="362" message="full block {} expected in the control structure" />
        <error source="T008" severity="info" line="368" message="keyword &apos;if&apos; not followed by a single space" />
        <error source="T012" severity="info" line="368" message="negation operator used in its short form" />
        <error source="T008" severity="info" line="370" message="keyword &apos;if&apos; not followed by a single space" />
        <error source="T008" severity="info" line="407" message="keyword &apos;if&apos; not followed by a single space" />
        <error source="T019" severity="info" line="408" message="full block {} expected in the control structure" />
        <error source="T008" severity="info" line="412" message="keyword &apos;if&apos; not followed by a single space" />
        <error source="T012" severity="info" line="412" message="negation operator used in its short form" />
        <error source="T019" severity="info" line="413" message="full block {} expected in the control structure" />
    </file>
</checkstyle>
