<?xml version="1.0" encoding="UTF-8"?>
<checkstyle version="5.0">
    <file name="c:\dev\kicad-personal\common\widgets\widget_net_selector.cpp">
        <error source="T008" severity="info" line="61" message="keyword &apos;for&apos; not followed by a single space" />
        <error source="T008" severity="info" line="63" message="keyword &apos;if&apos; not followed by a single space" />
        <error source="T008" severity="info" line="78" message="keyword &apos;for&apos; not followed by a single space" />
        <error source="T008" severity="info" line="80" message="keyword &apos;if&apos; not followed by a single space" />
        <error source="T019" severity="info" line="81" message="full block {} expected in the control structure" />
        <error source="T008" severity="info" line="90" message="keyword &apos;if&apos; not followed by a single space" />
        <error source="T019" severity="info" line="91" message="full block {} expected in the control structure" />
        <error source="T008" severity="info" line="101" message="keyword &apos;for&apos; not followed by a single space" />
        <error source="T008" severity="info" line="118" message="keyword &apos;for&apos; not followed by a single space" />
    </file>
</checkstyle>
